dynseqalign.cp37-win32.pyd
linmdtw/__init__.py
linmdtw/_version.py
linmdtw/alignmenttools.py
linmdtw/audiotools.py
linmdtw/dtw.py
linmdtw/dtwapprox.py
linmdtw/dtwgpu.py
linmdtw-0.1.3.dist-info/LICENSE
linmdtw-0.1.3.dist-info/METADATA
linmdtw-0.1.3.dist-info/WHEEL
linmdtw-0.1.3.dist-info/top_level.txt
linmdtw-0.1.3.dist-info/RECORD
