Metadata-Version: 2.1
Name: linmdtw
Version: 0.1.3
Summary: A linear memory, exact, parallelizable algorithm for dynamic time warping in arbitrary Euclidean spaces
Home-page: UNKNOWN
Author: Chris Tralie
Author-email: ctralie@alumni.princeton.edu
License: Apache2
Keywords: dynamic time warping,alignment,fast dtw,synchronization,time series,music information retrieval,audio analysis
Platform: UNKNOWN
Classifier: Intended Audience :: Science/Research
Classifier: Intended Audience :: Education
Classifier: Intended Audience :: Financial and Insurance Industry
Classifier: Intended Audience :: Healthcare Industry
Classifier: Topic :: Scientific/Engineering :: Information Analysis
Classifier: Topic :: Scientific/Engineering :: Mathematics
Classifier: Topic :: Multimedia :: Sound/Audio :: Analysis
Classifier: License :: OSI Approved :: MIT License
Classifier: Programming Language :: Python :: 3.6
Classifier: Programming Language :: Python :: 3.7
Classifier: Programming Language :: Python :: 3.8
Requires-Python: >=3.6
Requires-Dist: Cython
Requires-Dist: numpy
Requires-Dist: matplotlib
Requires-Dist: scipy
Requires-Dist: numba
Provides-Extra: docs
Requires-Dist: linmdtw-docs-config ; extra == 'docs'
Provides-Extra: examples
Provides-Extra: testing
Requires-Dist: pytest ; extra == 'testing'
